springtime/__init__.py
springtime/config.py
springtime/dummy.py
springtime/main.py
springtime/utils.py
springtime/datasets/__init__.py
springtime/datasets/abstract.py
springtime/datasets/appeears.py
springtime/datasets/daymet.py
springtime/datasets/eobs.py
springtime/datasets/pep725.py
springtime/datasets/phenocam.py
springtime/datasets/ppo.py
springtime/datasets/rnpn.py
springtime/models/__init__.py
springtime/models/basinhopper.py
springtime/models/loss_functions.py
springtime/models/phenology_models/__init__.py
springtime/models/phenology_models/phenology_model.py
springtime/models/phenology_models/thermaltime.py
springtime-0.2.2.dist-info/METADATA
springtime-0.2.2.dist-info/WHEEL
springtime-0.2.2.dist-info/entry_points.txt
springtime-0.2.2.dist-info/licenses/LICENSE
springtime-0.2.2.dist-info/RECORD
