Metadata-Version: 2.3
Name: springtime
Version: 0.2.2
Summary: Spatiotemporal phenology research with interpretable models
Project-URL: Documentation, https://springtime.readthedocs.io/en/latest/
Project-URL: Issues, https://github.com/phenology/springtime/issues
Project-URL: Source, https://github.com/phenology/springtime
Author-email: Peter Kalverla <peter.kalverla@gmx.com>
License-Expression: Apache-2.0
License-File: LICENSE
Keywords: phenology
Classifier: Development Status :: 4 - Beta
Classifier: Intended Audience :: Science/Research
Classifier: License :: OSI Approved :: Apache Software License
Classifier: Programming Language :: Python
Classifier: Programming Language :: Python :: 3.7
Classifier: Programming Language :: Python :: 3.8
Classifier: Programming Language :: Python :: 3.9
Classifier: Programming Language :: Python :: 3.10
Classifier: Programming Language :: Python :: 3.11
Classifier: Programming Language :: Python :: Implementation :: CPython
Classifier: Programming Language :: Python :: Implementation :: PyPy
Requires-Python: >=3.10
Requires-Dist: cftime
Requires-Dist: click
Requires-Dist: dask
Requires-Dist: geopandas
Requires-Dist: netcdf4
Requires-Dist: pandas
Requires-Dist: pydantic==2.*
Requires-Dist: pyyaml
Requires-Dist: requests
Requires-Dist: scikit-learn
Requires-Dist: xarray==2023.8.0
Requires-Dist: xdg-base-dirs
Provides-Extra: dev
Requires-Dist: black; extra == 'dev'
Requires-Dist: mypy; extra == 'dev'
Requires-Dist: pytest; extra == 'dev'
Requires-Dist: ruff; extra == 'dev'
Requires-Dist: types-pyyaml; extra == 'dev'
Requires-Dist: types-requests; extra == 'dev'
Provides-Extra: docs
Requires-Dist: mkdocs; extra == 'docs'
Requires-Dist: mkdocs-gen-files; extra == 'docs'
Requires-Dist: mkdocs-include-markdown-plugin; extra == 'docs'
Requires-Dist: mkdocs-jupyter; extra == 'docs'
Requires-Dist: mkdocs-literate-nav; extra == 'docs'
Requires-Dist: mkdocs-material; extra == 'docs'
Requires-Dist: mkdocs-section-index; extra == 'docs'
Requires-Dist: mkdocstrings-python; extra == 'docs'
Requires-Dist: mkdocstrings[python]; extra == 'docs'
Provides-Extra: extras
Requires-Dist: dumme; extra == 'extras'
Requires-Dist: ipykernel; extra == 'extras'
Requires-Dist: pycaret[models]; extra == 'extras'
Requires-Dist: pyphenology; extra == 'extras'
